loxodo_curses/__init__.py
loxodo_curses/__main__.py
loxodo_curses/utils.py
loxodo_curses/vault.py
loxodo_curses/vault_utils.py
loxodo_curses/curses_utils/__init__.py
loxodo_curses/curses_utils/list1.py
loxodo_curses/twofish/__init__.py
loxodo_curses/twofish/twofish.py
loxodo_curses/twofish/twofish_cbc.py
loxodo_curses/twofish/twofish_ecb.py
loxodo_curses-0.28.3.dist-info/METADATA
loxodo_curses-0.28.3.dist-info/WHEEL
loxodo_curses-0.28.3.dist-info/entry_points.txt
loxodo_curses-0.28.3.dist-info/licenses/LICENSE.txt
loxodo_curses-0.28.3.dist-info/RECORD
